{
    "view": {
        "attributes": {
            "_id": "test",
            "bg.color": "#ffffff",
            "padding.top": 90,
            "status_bar_style": "dark"
        },
        "controls": [
            {
                "_id": "customHeader",
                "_type": "Custom",
                "attributes": {
                    "control_location": "../custom/header.json",
                    "layoutType": "float",
                    "margin.top": 20,
                    "size.h": 50,
                    "size.w": "100%",
                    "title": "IXTouchID"
                }
            },
            {
                "_id": "touchIDTest",
                "_type": "TouchID",
                "actions": [
                    {
                        "_type": "Alert",
                        "attributes": {
                            "title": "Authenticated Successfully!"
                        },
                        "on": "success"
                    }
                ],
                "attributes": {
                    "title": "Please Authenticate"
                }
            },
            {
                "_id": "button",
                "_type": "Button",
                "actions": [
                    {
                        "_type": "Function",
                        "attributes": {
                            "_target": "touchIDTest",
                            "functionName": "authenticate"
                        },
                        "on": "touchUp"
                    }
                ],
                "attributes": {
                    "align.h": "center",
                    "align.v": "middle",
                    "bg.color": "cdcdcd",
                    "border.radius": 0,
                    "color": "6c6c6c",
                    "layoutType": "absolute",
                    "size.h": 50,
                    "size.w": 200,
                    "text": "Papers, please!",
                    "touch.bg.color": "cdcdcd",
                    "touch.color": "6c6c6c50"
                }
            }
        ],
        "datasources": []
    }
}